[{"id":1112879,"title":"一款全新的工作流 IDE","replyCount":440,"avatar":"https://cdn.v2ex.com/gravatar/e42dfa3b18137fa81fbef60a5bb92e8f?s=48&d=retro","username":"BlackHole1","lastReplyUsername":"TooFar","lastReplyDateAgo":"5 分钟前","lastReplyDate":"2025-02-20 23:35:16","nodeTitle":"分享创造","nodeUrl":"create","isTop":true},{"id":1112820,"title":"不抽烟，每次去女朋友家的时候要对每个人发烟吗","replyCount":226,"avatar":"https://cdn.v2ex.com/gravatar/35d0b7740fbe8fff578ee50a44dbd488?s=48&d=retro","username":"tomiaa","lastReplyUsername":"hefish","lastReplyDateAgo":"几秒前","lastReplyDate":"2025-02-20 23:39:39","nodeTitle":"生活","nodeUrl":"life","isTop":false},{"id":1112830,"title":"你二刷过哪些电影？","replyCount":168,"avatar":"https://cdn.v2ex.com/avatar/8799/296c/572158_large.png?m=1715838446","username":"sevenyangcc","lastReplyUsername":"moefishtang","lastReplyDateAgo":"1 小时 27 分钟前","lastReplyDate":"2025-02-20 22:12:31","nodeTitle":"电影","nodeUrl":"movie","isTop":false},{"id":1112828,"title":"徕芬的吹风机怎么样?","replyCount":116,"avatar":"https://cdn.v2ex.com/avatar/114b/9867/671969_large.png?m=1712498301","username":"ZeekChatCom","lastReplyUsername":"holyfinger","lastReplyDateAgo":"1 小时 12 分钟前","lastReplyDate":"2025-02-20 22:27:38","nodeTitle":"生活","nodeUrl":"life","isTop":false},{"id":1112917,"title":"年前离职后暂时加入了 V 友的创业团队, 现在产品前景不太好, 再找找新工作!","replyCount":105,"avatar":"https://cdn.v2ex.com/avatar/e919/6499/649046_large.png?m=1728659673","username":"NerdHND","lastReplyUsername":"kk2syc","lastReplyDateAgo":"50 分钟前","lastReplyDate":"2025-02-20 22:49:22","nodeTitle":"求职","nodeUrl":"cv","isTop":false},{"id":1112836,"title":"首次购车， 10 公里通勤公路车推荐","replyCount":89,"avatar":"https://cdn.v2ex.com/gravatar/0af499d345594fe682c42e640d2d8b58?s=48&d=retro","username":"tbv","lastReplyUsername":"Fish1024","lastReplyDateAgo":"8 分钟前","lastReplyDate":"2025-02-20 23:31:53","nodeTitle":"骑行","nodeUrl":"bike","isTop":false},{"id":1112809,"title":"三十岁后还有不焦虑失业的么","replyCount":84,"avatar":"https://cdn.v2ex.com/gravatar/c35f7b0565b919a76d95493cc50fea66?s=48&d=retro","username":"jasonjun","lastReplyUsername":"vorabend","lastReplyDateAgo":"44 分钟前","lastReplyDate":"2025-02-20 22:56:11","nodeTitle":"职场话题","nodeUrl":"career","isTop":false},{"id":1112859,"title":"小舅子生病有感...","replyCount":64,"avatar":"https://cdn.v2ex.com/avatar/458d/470e/393756_large.png?m=1730985720","username":"Guidoo","lastReplyUsername":"Guidoo","lastReplyDateAgo":"2 分钟前","lastReplyDate":"2025-02-20 23:37:39","nodeTitle":"健康","nodeUrl":"fit","isTop":false},{"id":1112810,"title":"面试没过，但亲戚说认识人可以安排","replyCount":61,"avatar":"https://cdn.v2ex.com/avatar/2faf/3b44/486923_large.png?m=1732258393","username":"YVAN7123","lastReplyUsername":"YVAN7123","lastReplyDateAgo":"5 小时 26 分钟前","lastReplyDate":"2025-02-20 18:13:54","nodeTitle":"职场话题","nodeUrl":"career","isTop":false},{"id":1112855,"title":"16E 居然砍了 Magsafe，吃相有点难看","replyCount":59,"avatar":"https://cdn.v2ex.com/avatar/b760/18c2/289728_large.png?m=1725606675","username":"GensKinsey","lastReplyUsername":"newarea","lastReplyDateAgo":"5 分钟前","lastReplyDate":"2025-02-20 23:34:23","nodeTitle":"iPhone","nodeUrl":"iphone","isTop":false},{"id":1112821,"title":"家里全屋定制打柜子求助","replyCount":59,"avatar":"https://cdn.v2ex.com/gravatar/16110c3793b3b44b23ebc2df75fed201?s=48&d=retro","username":"qwer666df","lastReplyUsername":"justdoitzZ","lastReplyDateAgo":"57 分钟前","lastReplyDate":"2025-02-20 22:43:10","nodeTitle":"装修","nodeUrl":"remodel","isTop":false},{"id":1112833,"title":"如果社保可以作为可选项，你是否会选择缴社保？","replyCount":56,"avatar":"https://cdn.v2ex.com/avatar/a1f4/9e70/489493_large.png?m=1740016283","username":"mmdou","lastReplyUsername":"agood","lastReplyDateAgo":"1 小时 58 分钟前","lastReplyDate":"2025-02-20 21:41:55","nodeTitle":"职场话题","nodeUrl":"career","isTop":false},{"id":1112829,"title":"只要求故障少，现在推荐哪辆车？","replyCount":55,"avatar":"https://cdn.v2ex.com/avatar/0ea8/f8be/585430_large.png?m=1735651724","username":"dcy7287","lastReplyUsername":"olia","lastReplyDateAgo":"14 分钟前","lastReplyDate":"2025-02-20 23:25:59","nodeTitle":"汽车","nodeUrl":"car","isTop":false},{"id":1112838,"title":"不想折腾 nas 家庭影院本地储存了，各种网盘有什么建议吗？","replyCount":53,"avatar":"https://cdn.v2ex.com/avatar/b316/d75e/520804_large.png?m=1735877117","username":"andyskaura","lastReplyUsername":"alfawei","lastReplyDateAgo":"2 小时 18 分钟前","lastReplyDate":"2025-02-20 21:21:24","nodeTitle":"NAS","nodeUrl":"nas","isTop":false},{"id":1112884,"title":"[送兑换码]DuRT—Mac 上的实时语音识别和翻译软件","replyCount":53,"avatar":"https://cdn.v2ex.com/gravatar/31485fa581ef83d77caf11cd48590a36?s=48&d=retro","username":"pimou","lastReplyUsername":"ydm9481","lastReplyDateAgo":"1 小时 40 分钟前","lastReplyDate":"2025-02-20 21:59:34","nodeTitle":"分享创造","nodeUrl":"create","isTop":false},{"id":1112850,"title":"目前杭州求职 25k 的薪资算高了吗？","replyCount":49,"avatar":"https://cdn.v2ex.com/gravatar/a8ba9e0844c5aa1701b0956e87243db9?s=48&d=retro","username":"liang723","lastReplyUsername":"whyrookie","lastReplyDateAgo":"13 分钟前","lastReplyDate":"2025-02-20 23:26:43","nodeTitle":"职场话题","nodeUrl":"career","isTop":false},{"id":1112873,"title":"今天接到了警察叔叔的反诈骗电话","replyCount":46,"avatar":"https://cdn.v2ex.com/avatar/9c8e/c915/674411_large.png?m=1711433392","username":"crocoBaby","lastReplyUsername":"yidinghe","lastReplyDateAgo":"2 分钟前","lastReplyDate":"2025-02-20 23:37:35","nodeTitle":"分享发现","nodeUrl":"share","isTop":false},{"id":1112878,"title":"iPhone16e 其实是一个不错的老人机","replyCount":44,"avatar":"https://cdn.v2ex.com/avatar/d1e6/275b/143510_large.png?m=1729913298","username":"leega0","lastReplyUsername":"agood","lastReplyDateAgo":"4 小时 38 分钟前","lastReplyDate":"2025-02-20 19:01:28","nodeTitle":"iPhone","nodeUrl":"iphone","isTop":false},{"id":1113000,"title":"今后貌似不用肉身去香港开港卡了？","replyCount":42,"avatar":"https://cdn.v2ex.com/avatar/b297/6079/673258_large.png?m=1722915568","username":"atao777","lastReplyUsername":"wowodavid","lastReplyDateAgo":"1 小时 24 分钟前","lastReplyDate":"2025-02-20 22:15:34","nodeTitle":"分享发现","nodeUrl":"share","isTop":false},{"id":1112937,"title":"机械革命现在品控如何？","replyCount":40,"avatar":"https://cdn.v2ex.com/avatar/257e/3a01/670465_large.png?m=1722351747","username":"Aicnal","lastReplyUsername":"wangsd","lastReplyDateAgo":"47 分钟前","lastReplyDate":"2025-02-20 22:52:50","nodeTitle":"计算机","nodeUrl":"computers","isTop":false},{"id":1112848,"title":"最近用 Cursor 分别开发了 Web、Android、iOS 的应用...","replyCount":39,"avatar":"https://cdn.v2ex.com/avatar/a082/effa/359061_large.png?m=1718330317","username":"ibrothergang","lastReplyUsername":"aleimu","lastReplyDateAgo":"5 小时 8 分钟前","lastReplyDate":"2025-02-20 18:31:21","nodeTitle":"程序员","nodeUrl":"programmer","isTop":false},{"id":1112813,"title":"求大佬指点， ai 加知识库的内部原理","replyCount":34,"avatar":"https://cdn.v2ex.com/gravatar/c5582a45a47b8fcef30fe130b3285b3d?s=48&d=retro","username":"oldManNewThought","lastReplyUsername":"sampeng","lastReplyDateAgo":"5 小时 32 分钟前","lastReplyDate":"2025-02-20 18:07:25","nodeTitle":"程序员","nodeUrl":"programmer","isTop":false},{"id":1112816,"title":"没人提 iPhone16e 集成了 C1 首款自研调制解调器 - 基带吗？","replyCount":34,"avatar":"https://cdn.v2ex.com/avatar/23be/c0ef/266992_large.png?m=1662600177","username":"penll","lastReplyUsername":"EthanZC","lastReplyDateAgo":"5 小时 46 分钟前","lastReplyDate":"2025-02-20 17:53:56","nodeTitle":"iPhone","nodeUrl":"iphone","isTop":false},{"id":1112847,"title":"了解电动车大单体电池价格","replyCount":33,"avatar":"https://cdn.v2ex.com/avatar/e66b/09b8/672073_large.png?m=1718335113","username":"guodonghao520","lastReplyUsername":"shakoon","lastReplyDateAgo":"15 分钟前","lastReplyDate":"2025-02-20 23:25:11","nodeTitle":"问与答","nodeUrl":"qna","isTop":false},{"id":1112944,"title":"有人喜欢写爬虫用浏览器扩展来实现的吗？","replyCount":33,"avatar":"https://cdn.v2ex.com/avatar/72e8/1de9/42293_large.png?m=1393046855","username":"s2555","lastReplyUsername":"NerdHND","lastReplyDateAgo":"13 分钟前","lastReplyDate":"2025-02-20 23:26:55","nodeTitle":"Python","nodeUrl":"python","isTop":false},{"id":1112802,"title":"是什么把 Linux 卡的“死死的” 既然谷歌 Pixel 是刷机最方便的，同时安卓又是 Linux 内核来的","replyCount":33,"avatar":"https://cdn.v2ex.com/gravatar/0f52ae06c426eec78cf5043021132462?s=48&d=retro","username":"wxmomomowx","lastReplyUsername":"levelworm","lastReplyDateAgo":"13 分钟前","lastReplyDate":"2025-02-20 23:26:51","nodeTitle":"Linux","nodeUrl":"linux","isTop":false},{"id":1112875,"title":"我有个设计网站，但是不知道怎么变现，友友们有啥好建议?","replyCount":31,"avatar":"https://cdn.v2ex.com/gravatar/91cee6487d4630d14ccbbd48c646985e?s=48&d=retro","username":"morestrive","lastReplyUsername":"morestrive","lastReplyDateAgo":"1 小时 38 分钟前","lastReplyDate":"2025-02-20 22:01:29","nodeTitle":"分享创造","nodeUrl":"create","isTop":false},{"id":1112892,"title":"想陪孩子玩体感游戏，借此锻炼身体，买 wii，还是 Switch？","replyCount":28,"avatar":"https://cdn.v2ex.com/avatar/ed76/9435/693918_large.png?m=1728288909","username":"apollo007","lastReplyUsername":"rxg9527","lastReplyDateAgo":"3 小时 0 分钟前","lastReplyDate":"2025-02-20 20:39:32","nodeTitle":"游戏","nodeUrl":"games","isTop":false},{"id":1112898,"title":"电动牙刷、冲牙器求推荐","replyCount":27,"avatar":"https://cdn.v2ex.com/avatar/d916/2956/417687_large.png?m=1735628093","username":"AlexShui","lastReplyUsername":"doodle77","lastReplyDateAgo":"2 小时 48 分钟前","lastReplyDate":"2025-02-20 20:51:44","nodeTitle":"生活","nodeUrl":"life","isTop":false},{"id":1113051,"title":"你认为目前最强的免费 AI 是什么？","replyCount":26,"avatar":"https://cdn.v2ex.com/gravatar/8b636c4819b9a61ed41a1e79c7e36b96?s=48&d=retro","username":"NianBroken","lastReplyUsername":"NGGTI","lastReplyDateAgo":"6 分钟前","lastReplyDate":"2025-02-20 23:33:22","nodeTitle":"程序员","nodeUrl":"programmer","isTop":false},{"id":1112899,"title":"我们做了个嵌入式 Linux OS (Debian 12) - tinyDebian OS，关于如何销售，大家有什么建议？","replyCount":25,"avatar":"https://cdn.v2ex.com/gravatar/f0fc3135a7edbc5712b61a4356249dfa?s=48&d=retro","username":"usb7","lastReplyUsername":"mrcn","lastReplyDateAgo":"50 分钟前","lastReplyDate":"2025-02-20 22:49:49","nodeTitle":"Linux","nodeUrl":"linux","isTop":false},{"id":1112897,"title":"写了个本版块老哥们应该会喜欢玩的脚本：自定义 B 站的 CDN（CCB）","replyCount":21,"avatar":"https://cdn.v2ex.com/avatar/b8a8/c05f/478739_large.png?m=1726622705","username":"kandaakihito","lastReplyUsername":"initialsky","lastReplyDateAgo":"1 小时 17 分钟前","lastReplyDate":"2025-02-20 22:22:25","nodeTitle":"宽带症候群","nodeUrl":"bb","isTop":false},{"id":1113020,"title":"现在的 VSCode 可以平替 JBr 系列吗","replyCount":21,"avatar":"https://cdn.v2ex.com/gravatar/f9fd0e47a762ec045123ad8879a63221?s=48&d=retro","username":"sunorg","lastReplyUsername":"me1onsoda","lastReplyDateAgo":"1 小时 36 分钟前","lastReplyDate":"2025-02-20 22:03:57","nodeTitle":"Visual Studio Code","nodeUrl":"vscode","isTop":false},{"id":1112853,"title":"CachyOS 看起来很适合极客/开发者","replyCount":19,"avatar":"https://cdn.v2ex.com/avatar/22e8/0fdc/73029_large.png?m=1736301227","username":"faywong8888","lastReplyUsername":"YsHaNg","lastReplyDateAgo":"3 小时 20 分钟前","lastReplyDate":"2025-02-20 20:20:01","nodeTitle":"Linux","nodeUrl":"linux","isTop":false},{"id":1112890,"title":"offer 二选一纠结","replyCount":19,"avatar":"https://cdn.v2ex.com/avatar/684b/5cf5/137952_large.png?m=1653023679","username":"cabbage","lastReplyUsername":"arischow","lastReplyDateAgo":"5 小时 21 分钟前","lastReplyDate":"2025-02-20 18:18:55","nodeTitle":"职场话题","nodeUrl":"career","isTop":false},{"id":1112835,"title":"电动车选购推荐","replyCount":18,"avatar":"https://cdn.v2ex.com/gravatar/cfae071df818fb86a98220d9b73c242e?s=48&d=retro","username":"shanex","lastReplyUsername":"SZP1206","lastReplyDateAgo":"3 小时 6 分钟前","lastReplyDate":"2025-02-20 20:33:36","nodeTitle":"生活","nodeUrl":"life","isTop":false},{"id":1112906,"title":"xAI 称 Grok 3 将免费提供","replyCount":18,"avatar":"https://cdn.v2ex.com/avatar/f997/c101/625465_large.png?m=1728551691","username":"mixuxin","lastReplyUsername":"lucacham","lastReplyDateAgo":"4 小时 32 分钟前","lastReplyDate":"2025-02-20 19:07:37","nodeTitle":"问与答","nodeUrl":"qna","isTop":false},{"id":1112865,"title":"这种情况如何判责？","replyCount":17,"avatar":"https://cdn.v2ex.com/avatar/55c0/f5bb/613964_large.png?m=1715911668","username":"1GM","lastReplyUsername":"evill","lastReplyDateAgo":"6 小时 55 分钟前","lastReplyDate":"2025-02-20 16:45:02","nodeTitle":"生活","nodeUrl":"life","isTop":false}]